{
  "pools": [
    {
      "rolls": 1,
      "entries": [
        {
          "type": "minecraft:item",
          "weight": 1,
          "functions": [
            {
              "function": "minecraft:set_nbt",
              "tag": "{BlockEntityTag:{id:\"minecraft:barrel\",Items:[{id:\"minecraft:structure_block\",Count:1b,tag:{CustomModelData:330000,tcc:{placed_block:1b,clear:1b,block:\"pottery_table\"}}}]},CustomModelData:330000,tcc:{id:\"pottery_table\"}}"
            },
            {
              "function": "minecraft:set_name",
              "name": {
                "translate": "block.tcc.pottery_table",
                "italic": false
              }
            },
            {
              "function": "minecraft:set_lore",
              "lore": [
                {
                  "translate": "pack.tcc",
                  "color": "#008725",
                  "italic": true
                }
              ]
            }
          ],
          "name": "minecraft:barrel"
        }
      ]
    }
  ],
  "random_sequence": "tcc:items/pottery_table"
}
