{
	"textures": {
		"body": "tcc:entity/sprouter/body",
		"neck": "tcc:entity/sprouter/neck/stage_0",
		"flippers": "tcc:entity/sprouter/flippers"
	},
	"elements": [
		{
			"from": [6.5, -4, 22],
			"to": [9.5, 5, 29],
			"rotation": {"angle": 0, "axis": "y", "origin": [16.5, 2, 32]},
			"faces": {
				"north": {"uv": [8.5, 12, 9.25, 14.25], "texture": "#body"},
				"east": {"uv": [9.25, 12, 11, 14.25], "texture": "#body"},
				"south": {"uv": [8.5, 12, 9.25, 14.25], "texture": "#body"},
				"west": {"uv": [9.25, 12, 11, 14.25], "texture": "#body"},
				"up": {"uv": [9.25, 16, 8.5, 14.25], "texture": "#body"},
				"down": {"uv": [9.25, 14.25, 8.5, 16], "texture": "#body"}
			}
		},
		{
			"from": [-10, -15.99, -8],
			"to": [-2, -9.99, 1],
			"rotation": {"angle": -22.5, "axis": "y", "origin": [1, -14, -3.5]},
			"faces": {
				"north": {"uv": [0, 0, 2, 1.5], "texture": "#flippers"},
				"east": {"uv": [4.25, 0, 6.5, 1.5], "texture": "#flippers"},
				"south": {"uv": [2, 0, 0, 1.5], "texture": "#flippers"},
				"west": {"uv": [2, 0, 4.25, 1.5], "texture": "#flippers"},
				"up": {"uv": [0, 3.75, 2, 1.5], "texture": "#flippers"},
				"down": {"uv": [4, 1.5, 2, 3.75], "texture": "#flippers"}
			}
		},
		{
			"from": [-10, -15.99, -8],
			"to": [-2, -9.99, 1],
			"rotation": {"angle": 0, "axis": "y", "origin": [1, -14, -3.5]},
			"faces": {
				"north": {"uv": [6.5, 0, 8.5, 1.5], "texture": "#flippers"},
				"east": {"uv": [10.75, 0, 13, 1.5], "texture": "#flippers"},
				"south": {"uv": [8.5, 0, 6.5, 1.5], "texture": "#flippers"},
				"west": {"uv": [8.5, 0, 10.75, 1.5], "texture": "#flippers"},
				"up": {"uv": [6.5, 3.75, 8.5, 1.5], "texture": "#flippers"},
				"down": {"uv": [10.5, 1.5, 8.5, 3.75], "texture": "#flippers"}
			}
		},
		{
			"from": [-10, -15.99, -8],
			"to": [-2, -9.99, 1],
			"rotation": {"angle": 22.5, "axis": "y", "origin": [1, -14, -3.5]},
			"faces": {
				"north": {"uv": [6.5, 3.75, 8.5, 5.25], "texture": "#flippers"},
				"east": {"uv": [10.75, 3.75, 13, 5.25], "texture": "#flippers"},
				"south": {"uv": [8.5, 3.75, 6.5, 5.25], "texture": "#flippers"},
				"west": {"uv": [8.5, 3.75, 10.75, 5.25], "texture": "#flippers"},
				"up": {"uv": [6.5, 7.5, 8.5, 5.25], "texture": "#flippers"},
				"down": {"uv": [10.5, 5.25, 8.5, 7.5], "texture": "#flippers"}
			}
		},
		{
			"from": [-10, -15.99, -8],
			"to": [-2, -9.99, 1],
			"rotation": {"angle": -22.5, "axis": "z", "origin": [1, -14, -3.5]},
			"faces": {
				"north": {"uv": [0, 3.75, 2, 5.25], "texture": "#flippers"},
				"east": {"uv": [4.25, 3.75, 6.5, 5.25], "texture": "#flippers"},
				"south": {"uv": [2, 3.75, 0, 5.25], "texture": "#flippers"},
				"west": {"uv": [2, 3.75, 4.25, 5.25], "texture": "#flippers"},
				"up": {"uv": [0, 7.5, 2, 5.25], "texture": "#flippers"},
				"down": {"uv": [4, 5.25, 2, 7.5], "texture": "#flippers"}
			}
		},
		{
			"from": [18, -15.99, -8],
			"to": [26, -9.99, 1],
			"rotation": {"angle": 22.5, "axis": "y", "origin": [15, -14, -3.5]},
			"faces": {
				"north": {"uv": [8.5, 3.75, 6.5, 5.25], "texture": "#flippers"},
				"east": {"uv": [10.75, 3.75, 8.5, 5.25], "texture": "#flippers"},
				"south": {"uv": [6.5, 3.75, 8.5, 5.25], "texture": "#flippers"},
				"west": {"uv": [10.75, 3.75, 13, 5.25], "texture": "#flippers"},
				"up": {"uv": [8.5, 7.5, 6.5, 5.25], "texture": "#flippers"},
				"down": {"uv": [8.5, 5.25, 10.5, 7.5], "texture": "#flippers"}
			}
		},
		{
			"from": [18, -15.99, -8],
			"to": [26, -9.99, 1],
			"rotation": {"angle": 0, "axis": "y", "origin": [15, -14, -3.5]},
			"faces": {
				"north": {"uv": [2, 3.75, 0, 5.25], "texture": "#flippers"},
				"east": {"uv": [2, 3.75, 4.25, 5.25], "texture": "#flippers"},
				"south": {"uv": [0, 3.75, 2, 5.25], "texture": "#flippers"},
				"west": {"uv": [4.25, 3.75, 6.5, 5.25], "texture": "#flippers"},
				"up": {"uv": [2, 7.5, 0, 5.25], "texture": "#flippers"},
				"down": {"uv": [2, 5.25, 4, 7.5], "texture": "#flippers"}
			}
		},
		{
			"from": [18, -15.99, -8],
			"to": [26, -9.99, 1],
			"rotation": {"angle": -22.5, "axis": "y", "origin": [15, -14, -3.5]},
			"faces": {
				"north": {"uv": [2, 0, 0, 1.5], "texture": "#flippers"},
				"east": {"uv": [2, 0, 4.25, 1.5], "texture": "#flippers"},
				"south": {"uv": [0, 0, 2, 1.5], "texture": "#flippers"},
				"west": {"uv": [4.25, 0, 6.5, 1.5], "texture": "#flippers"},
				"up": {"uv": [2, 3.75, 0, 1.5], "texture": "#flippers"},
				"down": {"uv": [2, 3.75, 4, 1.5], "texture": "#flippers"}
			}
		},
		{
			"from": [18, -15.99, -8],
			"to": [26, -9.99, 1],
			"rotation": {"angle": 22.5, "axis": "z", "origin": [15, -14, -3.5]},
			"faces": {
				"north": {"uv": [8.5, 0, 6.5, 1.5], "texture": "#flippers"},
				"east": {"uv": [8.5, 0, 10.75, 1.5], "texture": "#flippers"},
				"south": {"uv": [6.5, 0, 8.5, 1.5], "texture": "#flippers"},
				"west": {"uv": [10.75, 0, 13, 1.5], "texture": "#flippers"},
				"up": {"uv": [8.5, 3.75, 6.5, 1.5], "texture": "#flippers"},
				"down": {"uv": [8.5, 1.5, 10.5, 3.75], "texture": "#flippers"}
			}
		},
		{
			"from": [-2, -16, -12],
			"to": [18, 0, 8],
			"rotation": {"angle": 0, "axis": "y", "origin": [8, -10, -2]},
			"faces": {
				"north": {"uv": [5, 0, 10, 4], "texture": "#body"},
				"east": {"uv": [0, 0, 5, 4], "texture": "#body"},
				"south": {"uv": [11, 4, 16, 8], "texture": "#body"},
				"west": {"uv": [10, 0, 15, 4], "texture": "#body"},
				"up": {"uv": [5, 7, 0, 12], "texture": "#body"},
				"down": {"uv": [10, 7, 5, 12], "texture": "#body"}
			}
		},
		{
			"from": [0, 0, -16],
			"to": [16, 32, 0],
			"rotation": {"angle": 0, "axis": "y", "origin": [10, 22, -6]},
			"faces": {
				"north": {"uv": [0, 0, 8, 16], "texture": "#neck"},
				"east": {"uv": [0, 0, 8, 16], "texture": "#neck"},
				"south": {"uv": [0, 0, 8, 16], "texture": "#neck"},
				"west": {"uv": [0, 0, 8, 16], "texture": "#neck"},
				"up": {"uv": [16, 0, 8, 8], "texture": "#neck"},
				"down": {"uv": [16, 8, 8, 16], "texture": "#neck"}
			}
		},
		{
			"from": [0, -6, -16],
			"to": [16, 0, -12],
			"rotation": {"angle": 0, "axis": "y", "origin": [10, 0, -6]},
			"faces": {
				"north": {"uv": [11, 14, 15, 15.5], "texture": "#body"},
				"east": {"uv": [16, 14, 15, 15.5], "texture": "#body"},
				"west": {"uv": [15, 14, 16, 15.5], "texture": "#body"}
			}
		},
		{
			"from": [3, -16, 8],
			"to": [13, -4, 32],
			"rotation": {"angle": 0, "axis": "y", "origin": [13, -10, 18]},
			"faces": {
				"north": {"uv": [0, 4, 2.5, 7], "texture": "#body"},
				"east": {"uv": [8.5, 4, 2.5, 7], "texture": "#body"},
				"south": {"uv": [0, 4, 2.5, 7], "texture": "#body"},
				"west": {"uv": [2.5, 4, 8.5, 7], "texture": "#body"},
				"up": {"uv": [13.5, 8, 11, 14], "texture": "#body"},
				"down": {"uv": [16, 8, 13.5, 14], "texture": "#body"}
			}
		},
		{
			"from": [6.5, -4, 14],
			"to": [9.5, 3, 19],
			"rotation": {"angle": 0, "axis": "y", "origin": [16.5, 2, 24]},
			"faces": {
				"north": {"uv": [6.5, 12, 7.25, 13.75], "texture": "#body"},
				"east": {"uv": [7.25, 12, 8.5, 13.75], "texture": "#body"},
				"south": {"uv": [6.5, 12, 7.25, 13.75], "texture": "#body"},
				"west": {"uv": [7.25, 12, 8.5, 13.75], "texture": "#body"},
				"up": {"uv": [7.25, 15, 6.5, 13.75], "texture": "#body"},
				"down": {"uv": [7.25, 13.75, 6.5, 15], "texture": "#body"}
			}
		}
	],
	"display": {
		"ground": {
			"rotation": [0, -180, 0],
			"translation": [0, -4.5, -15.2],
			"scale": [0.55, 0.55, 0.55]
		}
	}
}