{
  "pools": [{
      "rolls": 1,
      "entries": [{
        "type": "item",
        "weight": 1,
        "name": "minecraft:ender_pearl",
        "functions": [{
            "function": "set_count",
            "count": {
              "min": 0,
              "max": 1
            }
          },
          {
            "function": "looting_enchant",
            "count": {
              "min": 0,
              "max": 1
            }
          }
        ]
      }]
    },
    {
      "rolls": 1,
      "conditions": [{
        "condition": "entity_properties",
        "entity": "killer",
        "predicate": {
          "nbt": "{powered:1b}"
        }
      }],
      "entries": [{
        "type": "loot_table",
        "weight": 1,
        "name": "tcc:items/enderman_head"
      }]
    }
  ]
}