{
  "parent": "tcc:recipes/root",
  "rewards": {
    "recipes": [
      "tcc:nbt/golden_chorus_fruit"
    ]
  },
  "criteria": {
    "has_chorus_fruit": {
      "trigger": "minecraft:inventory_changed",
      "conditions": {
        "items": [
          {
            "items": [
              "minecraft:chorus_fruit"
            ]
          }
        ]
      }
    },
    "has_the_recipe": {
      "trigger": "minecraft:recipe_unlocked",
      "conditions": {
        "recipe": "tcc:nbt/golden_chorus_fruit"
      }
    }
  },
  "requirements": [
    [
      "has_chorus_fruit",
      "has_the_recipe"
    ]
  ]
}
