{
  "pools": [
    {
      "rolls": 1,
      "entries": [
        {
          "type": "minecraft:item",
          "weight": 1,
          "name": "minecraft:map",
          "functions": [
            {
              "function": "minecraft:exploration_map",
              "destination": "tcc:jungle_explorer_map_located",
              "decoration": "minecraft:target_point",
              "zoom": 1,
              "search_radius": 50,
              "skip_existing_chunks": true
            },
            {
              "function": "minecraft:set_name",
              "name": {
                "translate": "item.tcc.jungle_explorer_map"
              },
              "target": "item_name"
            },
            {
              "function": "minecraft:set_custom_data",
              "tag": "{tcc:{id:\"jungle_explorer_map\"}}"
            },
            {
              "function": "minecraft:set_components",
              "components": {
                "minecraft:map_color": 3641177
              }
            },
            {
              "function": "minecraft:set_lore",
              "lore": [
                {
                  "translate": "pack.tcc",
                  "color": "#008725",
                  "italic": true
                }
              ],
              "mode": "replace_all"
            }
          ]
        }
      ]
    }
  ],
  "random_sequence": "tcc:items/jungle_explorer_map"
}
