[
  {
    "condition": "minecraft:random_chance",
    "chance": 0.4
  },
  {
    "condition": "minecraft:alternative",
    "terms": [
      {
        "condition": "minecraft:entity_properties",
        "entity": "this",
        "predicate": {
          "location": {
            "biome": "minecraft:deep_warm_ocean"
          }
        }
      },
      {
        "condition": "minecraft:entity_properties",
        "entity": "this",
        "predicate": {
          "location": {
            "biome": "minecraft:warm_ocean"
          }
        }
      }
    ]
  }
]
