{
  "category": "equipment",
  "type": "crafting_shaped",
  "pattern": [
    "L##",
    "  #",
    "  L"
  ],
  "key": {
    "#": "#minecraft:planks",
    "L": "minecraft:leather"
  },
  "result": {
    "id": "minecraft:warped_fungus_on_a_stick",
    "count": 1,
    "components": {
      "minecraft:item_model": "tcc:boomerang",
      "minecraft:damage": 0,
      "minecraft:max_damage": 300,
      "minecraft:custom_data": {
        "tcc": {
          "id": "boomerang"
        }
      },
      "minecraft:repairable": {
        "items": "#tcc:repair_items/boomerang"
      },
      "minecraft:item_name": {"translate":"item.tcc.boomerang"},
      "minecraft:lore": [
        {"translate":"pack.tcc","color":"#008725","italic":true}
      ]
    }
  }
}
