{
  "pools": [
    {
      "rolls": 1,
      "entries": [
        {
          "type": "minecraft:item",
          "weight": 1,
          "functions": [
            {
              "function": "minecraft:set_nbt",
              "tag": "{CustomModelData:338005,tcc:{gemstone:{id:\"minecraft:lapis_lazuli\",quality:\"cut\"},id:\"ring\",metal:\"minecraft:iron\",durability:[100,100],repaired:1b},Unbreakable:1b,HideFlags:4}"
            },
            {
              "function": "minecraft:set_name",
              "name": {
                "translate": "item.tcc.ring.gemstone.lapis_lazuli",
                "italic": false
              }
            },
            {
              "function": "set_lore",
              "lore": [
                {
                  "translate": "item.durability",
                  "with": [
                    100,
                    100
                  ],
                  "italic": false,
                  "color": "gray"
                },
                {
                  "translate": "pack.tcc",
                  "color": "#008725",
                  "italic": true
                },
                "",
                {
                  "translate": "item.modifiers.offhand",
                  "italic": false,
                  "color": "gray"
                },
                {
                  "translate": "attribute.modifier.plus.0",
                  "italic": false,
                  "color": "blue",
                  "with": [
                    "1",
                    {
                      "translate": "attribute.name.tcc.mob_xp_bonus"
                    }
                  ]
                }
              ],
              "entity": "this"
            }
          ],
          "name": "minecraft:carrot_on_a_stick"
        }
      ]
    }
  ]
}