{
  "elements": [
    {
      "element": {
        "element_type": "minecraft:single_pool_element",
        "location": "tcc:village/mangrove_swamp/zombie/houses/small_house_1",
        "processors": "tcc:village/mangrove_swamp/zombie",
        "projection": "rigid"
      },
      "weight": 2
    },
    {
      "element": {
        "element_type": "minecraft:single_pool_element",
        "location": "tcc:village/mangrove_swamp/zombie/houses/small_house_2",
        "processors": "tcc:village/mangrove_swamp/zombie",
        "projection": "rigid"
      },
      "weight": 2
    },
    {
      "element": {
        "element_type": "minecraft:single_pool_element",
        "location": "tcc:village/mangrove_swamp/zombie/houses/small_house_3",
        "processors": "tcc:village/mangrove_swamp/zombie",
        "projection": "rigid"
      },
      "weight": 2
    },
    {
      "element": {
        "element_type": "minecraft:single_pool_element",
        "location": "tcc:village/mangrove_swamp/zombie/houses/small_house_4",
        "processors": "tcc:village/mangrove_swamp/zombie",
        "projection": "rigid"
      },
      "weight": 2
    },
    {
      "element": {
        "element_type": "minecraft:single_pool_element",
        "location": "tcc:village/mangrove_swamp/zombie/houses/small_house_5",
        "processors": "tcc:village/mangrove_swamp/zombie",
        "projection": "rigid"
      },
      "weight": 2
    },
    {
      "element": {
        "element_type": "minecraft:single_pool_element",
        "location": "tcc:village/mangrove_swamp/zombie/houses/small_house_6",
        "processors": "tcc:village/mangrove_swamp/zombie",
        "projection": "rigid"
      },
      "weight": 2
    },
    {
      "element": {
        "element_type": "minecraft:single_pool_element",
        "location": "tcc:village/mangrove_swamp/zombie/houses/small_house_7",
        "processors": "tcc:village/mangrove_swamp/zombie",
        "projection": "rigid"
      },
      "weight": 2
    },
    {
      "element": {
        "element_type": "minecraft:single_pool_element",
        "location": "tcc:village/mangrove_swamp/zombie/houses/medium_house_1",
        "processors": "tcc:village/mangrove_swamp/zombie",
        "projection": "rigid"
      },
      "weight": 2
    },
    {
      "element": {
        "element_type": "minecraft:single_pool_element",
        "location": "tcc:village/mangrove_swamp/zombie/houses/medium_house_2",
        "processors": "tcc:village/mangrove_swamp/zombie",
        "projection": "rigid"
      },
      "weight": 2
    },
    {
      "element": {
        "element_type": "minecraft:single_pool_element",
        "location": "tcc:village/mangrove_swamp/zombie/houses/medium_house_3",
        "processors": "tcc:village/mangrove_swamp/zombie",
        "projection": "rigid"
      },
      "weight": 2
    },
    {
      "element": {
        "element_type": "minecraft:single_pool_element",
        "location": "tcc:village/mangrove_swamp/zombie/houses/big_house",
        "processors": "tcc:village/mangrove_swamp/zombie",
        "projection": "rigid"
      },
      "weight": 3
    },
    {
      "element": {
        "element_type": "minecraft:single_pool_element",
        "location": "tcc:village/mangrove_swamp/zombie/houses/butcher",
        "processors": "tcc:village/mangrove_swamp/zombie",
        "projection": "rigid"
      },
      "weight": 2
    },
    {
      "element": {
        "element_type": "minecraft:single_pool_element",
        "location": "tcc:village/mangrove_swamp/zombie/houses/toolsmith",
        "processors": "tcc:village/mangrove_swamp/zombie",
        "projection": "rigid"
      },
      "weight": 2
    },
    {
      "element": {
        "element_type": "minecraft:single_pool_element",
        "location": "tcc:village/mangrove_swamp/zombie/houses/fletcher",
        "processors": "tcc:village/mangrove_swamp/zombie",
        "projection": "rigid"
      },
      "weight": 2
    },
    {
      "element": {
        "element_type": "minecraft:single_pool_element",
        "location": "tcc:village/mangrove_swamp/zombie/houses/shepherd",
        "processors": "tcc:village/mangrove_swamp/zombie",
        "projection": "rigid"
      },
      "weight": 2
    },
    {
      "element": {
        "element_type": "minecraft:single_pool_element",
        "location": "tcc:village/mangrove_swamp/zombie/houses/armorer",
        "processors": "tcc:village/mangrove_swamp/zombie",
        "projection": "rigid"
      },
      "weight": 2
    },
    {
      "element": {
        "element_type": "minecraft:single_pool_element",
        "location": "tcc:village/mangrove_swamp/zombie/houses/fisherman",
        "processors": "tcc:village/mangrove_swamp/zombie",
        "projection": "rigid"
      },
      "weight": 2
    },
    {
      "element": {
        "element_type": "minecraft:single_pool_element",
        "location": "tcc:village/mangrove_swamp/zombie/houses/leatherworker",
        "processors": "tcc:village/mangrove_swamp/zombie",
        "projection": "rigid"
      },
      "weight": 2
    },
    {
      "element": {
        "element_type": "minecraft:single_pool_element",
        "location": "tcc:village/mangrove_swamp/zombie/houses/cartographer",
        "processors": "tcc:village/mangrove_swamp/zombie",
        "projection": "rigid"
      },
      "weight": 2
    },
    {
      "element": {
        "element_type": "minecraft:single_pool_element",
        "location": "tcc:village/mangrove_swamp/zombie/houses/librarian",
        "processors": "tcc:village/mangrove_swamp/zombie",
        "projection": "rigid"
      },
      "weight": 2
    },
    {
      "element": {
        "element_type": "minecraft:single_pool_element",
        "location": "tcc:village/mangrove_swamp/zombie/houses/mason",
        "processors": "tcc:village/mangrove_swamp/zombie",
        "projection": "rigid"
      },
      "weight": 2
    },
    {
      "element": {
        "element_type": "minecraft:single_pool_element",
        "location": "tcc:village/mangrove_swamp/zombie/houses/weaponsmith",
        "processors": "tcc:village/mangrove_swamp/zombie",
        "projection": "rigid"
      },
      "weight": 3
    },
    {
      "element": {
        "element_type": "minecraft:single_pool_element",
        "location": "tcc:village/mangrove_swamp/zombie/houses/cleric",
        "processors": "tcc:village/mangrove_swamp/zombie",
        "projection": "rigid"
      },
      "weight": 3
    },
    {
      "element": {
        "element_type": "minecraft:single_pool_element",
        "location": "tcc:village/mangrove_swamp/zombie/houses/farm_1",
        "processors": "tcc:village/mangrove_swamp/zombie",
        "projection": "rigid"
      },
      "weight": 3
    },
    {
      "element": {
        "element_type": "minecraft:single_pool_element",
        "location": "tcc:village/mangrove_swamp/zombie/houses/farm_2",
        "processors": "tcc:village/mangrove_swamp/zombie",
        "projection": "rigid"
      },
      "weight": 3
    },
    {
      "element": {
        "element_type": "minecraft:single_pool_element",
        "location": "tcc:village/mangrove_swamp/zombie/houses/snail_pen_1",
        "processors": "tcc:village/mangrove_swamp/zombie",
        "projection": "rigid"
      },
      "weight": 2
    },
    {
      "element": {
        "element_type": "minecraft:single_pool_element",
        "location": "tcc:village/mangrove_swamp/zombie/houses/snail_pen_2",
        "processors": "tcc:village/mangrove_swamp/zombie",
        "projection": "rigid"
      },
      "weight": 2
    },
    {
      "element": {
        "element_type": "minecraft:single_pool_element",
        "location": "tcc:village/mangrove_swamp/zombie/houses/archaeologist",
        "processors": "tcc:village/mangrove_swamp/zombie",
        "projection": "rigid"
      },
      "weight": 2
    },
    {
      "element": {
        "element_type": "minecraft:empty_pool_element"
      },
      "weight": 6
    }
  ],
  "fallback": "tcc:village/mangrove_swamp/terminators"
}